seqprops/__init__.py
seqprops/seqprops.py
seqprops/data/__init__.py
seqprops/data/aadata.csv
seqprops-1.0.2.dist-info/METADATA
seqprops-1.0.2.dist-info/WHEEL
seqprops-1.0.2.dist-info/top_level.txt
seqprops-1.0.2.dist-info/RECORD
