Metadata-Version: 2.1
Name: seqprops
Version: 1.0.2
Home-page: https://github.com/eotovic/seqprops
Author: Erik Otović
Author-email: erik.otovic@gmail.com
License: GPL3
Keywords: sequential properties physicochemical machine learning peptides proteins
Requires-Dist: pandas
Requires-Dist: numpy
Requires-Dist: scikit-learn
Requires-Dist: dask
Requires-Dist: distributed
